thds/attrs_utils/__init__.py
thds/attrs_utils/defaults.py
thds/attrs_utils/docs.py
thds/attrs_utils/empty.py
thds/attrs_utils/py.typed
thds/attrs_utils/recursion.py
thds/attrs_utils/registry.py
thds/attrs_utils/type_cache.py
thds/attrs_utils/type_recursion.py
thds/attrs_utils/type_utils.py
thds/attrs_utils/utils.py
thds/attrs_utils/cattrs/__init__.py
thds/attrs_utils/cattrs/converter.py
thds/attrs_utils/cattrs/errors.py
thds/attrs_utils/isinstance/__init__.py
thds/attrs_utils/isinstance/check.py
thds/attrs_utils/isinstance/registry.py
thds/attrs_utils/isinstance/util.py
thds/attrs_utils/jsonschema/__init__.py
thds/attrs_utils/jsonschema/constructors.py
thds/attrs_utils/jsonschema/jsonschema.py
thds/attrs_utils/jsonschema/str_formats.py
thds/attrs_utils/jsonschema/util.py
thds/attrs_utils/params/__init__.py
thds/attrs_utils/params/parameterize.py
thds/attrs_utils/params/records.py
thds/attrs_utils/params/utils.py
thds/attrs_utils/random/__init__.py
thds/attrs_utils/random/attrs.py
thds/attrs_utils/random/builtin.py
thds/attrs_utils/random/collection.py
thds/attrs_utils/random/gen.py
thds/attrs_utils/random/optional.py
thds/attrs_utils/random/registry.py
thds/attrs_utils/random/tuple.py
thds/attrs_utils/random/union.py
thds/attrs_utils/random/util.py
thds_attrs_utils-1.7.20260130200337.dist-info/METADATA
thds_attrs_utils-1.7.20260130200337.dist-info/WHEEL
thds_attrs_utils-1.7.20260130200337.dist-info/top_level.txt
thds_attrs_utils-1.7.20260130200337.dist-info/RECORD
