Metadata-Version: 2.4
Name: thds.attrs-utils
Version: 1.7.20260130200337
Summary: Utilities for attrs record classes.
Author-email: Trillianth Health <info@trillianthealth.com>
Project-URL: Repository, https://github.com/TrilliantHealth/ds-monorepo
Requires-Python: >=3.9
Requires-Dist: attrs>=22.2.0
Requires-Dist: returns
Requires-Dist: thds-core
Requires-Dist: typing-inspect
Provides-Extra: cattrs
Requires-Dist: cattrs>=22.2.0; extra == "cattrs"
Provides-Extra: docstrings
Requires-Dist: docstring-parser; extra == "docstrings"
Provides-Extra: jsonschema
Requires-Dist: fastjsonschema; extra == "jsonschema"
